perlin_noise_ex/__init__.py
perlin_noise_ex/noise.py
perlin_noise_ex-0.1.3.dist-info/licenses/LICENSE
perlin_noise_ex-0.1.3.dist-info/METADATA
perlin_noise_ex-0.1.3.dist-info/WHEEL
perlin_noise_ex-0.1.3.dist-info/top_level.txt
perlin_noise_ex-0.1.3.dist-info/RECORD
