Metadata-Version: 2.4
Name: perlin_noise_ex
Version: 0.1.3
Summary: Python implementation of Perlin noise generator
Author-email: Exityx <gdlasorum@gmail.com>
Project-URL: Homepage, https://github.com/ExityxXx/PerlinNoiseEX
Classifier: Programming Language :: Python :: 3
Classifier: License :: OSI Approved :: MIT License
Classifier: Operating System :: OS Independent
Requires-Python: >=3.7
License-File: LICENSE
Requires-Dist: numpy
Requires-Dist: matplotlib
Requires-Dist: perlin-noise
Dynamic: license-file
